{
  "X1ZPRFO480" : {
    "chocolates" : [ {
      "id" : "5",
      "name" : "Milka cokolada",
      "price" : 3.5,
      "type" : "Cokolada za jelo",
      "flavor" : "mlecna",
      "grams" : 300.0,
      "description" : "Najlepsa cokolada na svetu!",
      "picture" : "https://encrypted-tbn0.gstatic.com/images?q=tbn:ANd9GcRM1bjLuveRZ6g0nUu_L_XeaMdK3oiyDk_HwA&s",
      "stockQuantity" : 35,
      "isInStock" : true,
      "fabricId" : "3",
      "isDeleted" : false
    } ],
    "factory" : {
      "chocolates" : [ ],
      "id" : "3",
      "name" : "The best",
      "businessHours" : "08:00 - 22:00",
      "isOpen" : true,
      "location" : {
        "longitude" : 21.3254,
        "latitude" : 25.7841234,
        "address" : {
          "street" : "Miroslava Antica 13",
          "city" : "Beocin",
          "postalCode" : "21300"
        }
      },
      "picture" : "https://w7.pngwing.com/pngs/12/661/png-transparent-danganronpa-trigger-happy-havoc-danganronpa-2-goodbye-despair-monokuma-1-t-shirt-manga-t-shirt-white-carnivoran-manga-thumbnail.png",
      "rating" : 3.1666666666666665
    },
    "id" : "X1ZPRFO480",
    "chocolateIds" : [ "5", "5", "5" ],
    "date" : "2024-06-30T14:26:07.4618074",
    "factoryId" : "3",
    "price" : 10.5,
    "customer" : "Milan Milanovic",
    "status" : "Accepted",
    "userId" : "5"
  },
  "9XZ9NXHZIR" : {
    "chocolates" : [ {
      "id" : "5",
      "name" : "Milka cokolada",
      "price" : 3.5,
      "type" : "Cokolada za jelo",
      "flavor" : "mlecna",
      "grams" : 300.0,
      "description" : "Najlepsa cokolada na svetu!",
      "picture" : "https://encrypted-tbn0.gstatic.com/images?q=tbn:ANd9GcRM1bjLuveRZ6g0nUu_L_XeaMdK3oiyDk_HwA&s",
      "stockQuantity" : 35,
      "isInStock" : true,
      "fabricId" : "3",
      "isDeleted" : false
    }, {
      "id" : "7",
      "name" : "daadad",
      "price" : 100.0,
      "type" : "aaaaaaaa",
      "flavor" : "aaaaaaaaa",
      "grams" : 22.0,
      "description" : "aaaaaaaa",
      "picture" : "aaaaaaaaaaaaaa",
      "stockQuantity" : 3,
      "isInStock" : true,
      "fabricId" : "3",
      "isDeleted" : false
    } ],
    "factory" : {
      "chocolates" : [ ],
      "id" : "3",
      "name" : "The best",
      "businessHours" : "08:00 - 22:00",
      "isOpen" : true,
      "location" : {
        "longitude" : 21.3254,
        "latitude" : 25.7841234,
        "address" : {
          "street" : "Miroslava Antica 13",
          "city" : "Beocin",
          "postalCode" : "21300"
        }
      },
      "picture" : "https://w7.pngwing.com/pngs/12/661/png-transparent-danganronpa-trigger-happy-havoc-danganronpa-2-goodbye-despair-monokuma-1-t-shirt-manga-t-shirt-white-carnivoran-manga-thumbnail.png",
      "rating" : 3.1666666666666665
    },
    "id" : "9XZ9NXHZIR",
    "chocolateIds" : [ "7", "7", "7", "5", "5" ],
    "date" : "2024-06-30T14:40:15.9015096",
    "factoryId" : "3",
    "price" : 307.0,
    "customer" : "Milan Milanovic",
    "status" : "InProgress",
    "userId" : "5"
  },
  "0MWNONGWEB" : {
    "chocolates" : [ {
      "id" : "5",
      "name" : "Milka cokolada",
      "price" : 3.5,
      "type" : "Cokolada za jelo",
      "flavor" : "mlecna",
      "grams" : 300.0,
      "description" : "Najlepsa cokolada na svetu!",
      "picture" : "https://encrypted-tbn0.gstatic.com/images?q=tbn:ANd9GcRM1bjLuveRZ6g0nUu_L_XeaMdK3oiyDk_HwA&s",
      "stockQuantity" : 35,
      "isInStock" : true,
      "fabricId" : "3",
      "isDeleted" : false
    } ],
    "factory" : {
      "chocolates" : [ ],
      "id" : "3",
      "name" : "The best",
      "businessHours" : "08:00 - 22:00",
      "isOpen" : true,
      "location" : {
        "longitude" : 21.3254,
        "latitude" : 25.7841234,
        "address" : {
          "street" : "Miroslava Antica 13",
          "city" : "Beocin",
          "postalCode" : "21300"
        }
      },
      "picture" : "https://w7.pngwing.com/pngs/12/661/png-transparent-danganronpa-trigger-happy-havoc-danganronpa-2-goodbye-despair-monokuma-1-t-shirt-manga-t-shirt-white-carnivoran-manga-thumbnail.png",
      "rating" : 3.1666666666666665
    },
    "id" : "0MWNONGWEB",
    "chocolateIds" : [ "5", "5" ],
    "date" : "2024-06-30T14:57:05.8164847",
    "factoryId" : "3",
    "price" : 7.0,
    "customer" : "Milan Milanovic",
    "status" : "Declined",
    "userId" : "5"
  },
  "0BZGNJGIHC" : {
    "chocolates" : [ {
      "id" : "5",
      "name" : "Milka cokolada",
      "price" : 3.5,
      "type" : "Cokolada za jelo",
      "flavor" : "mlecna",
      "grams" : 300.0,
      "description" : "Najlepsa cokolada na svetu!",
      "picture" : "https://encrypted-tbn0.gstatic.com/images?q=tbn:ANd9GcRM1bjLuveRZ6g0nUu_L_XeaMdK3oiyDk_HwA&s",
      "stockQuantity" : 35,
      "isInStock" : true,
      "fabricId" : "3",
      "isDeleted" : false
    } ],
    "factory" : {
      "chocolates" : [ ],
      "id" : "3",
      "name" : "The best",
      "businessHours" : "08:00 - 22:00",
      "isOpen" : true,
      "location" : {
        "longitude" : 21.3254,
        "latitude" : 25.7841234,
        "address" : {
          "street" : "Miroslava Antica 13",
          "city" : "Beocin",
          "postalCode" : "21300"
        }
      },
      "picture" : "https://w7.pngwing.com/pngs/12/661/png-transparent-danganronpa-trigger-happy-havoc-danganronpa-2-goodbye-despair-monokuma-1-t-shirt-manga-t-shirt-white-carnivoran-manga-thumbnail.png",
      "rating" : 3.1666666666666665
    },
    "id" : "0BZGNJGIHC",
    "chocolateIds" : [ "5", "5", "5" ],
    "date" : "2024-06-30T14:28:51.9445259",
    "factoryId" : "3",
    "price" : 10.5,
    "customer" : "Milan Milanovic",
    "status" : "InProgress",
    "userId" : "5"
  },
  "S4JFKE0QF2" : {
    "chocolates" : [ {
      "id" : "5",
      "name" : "Milka cokolada",
      "price" : 3.5,
      "type" : "Cokolada za jelo",
      "flavor" : "mlecna",
      "grams" : 300.0,
      "description" : "Najlepsa cokolada na svetu!",
      "picture" : "https://encrypted-tbn0.gstatic.com/images?q=tbn:ANd9GcRM1bjLuveRZ6g0nUu_L_XeaMdK3oiyDk_HwA&s",
      "stockQuantity" : 35,
      "isInStock" : true,
      "fabricId" : "3",
      "isDeleted" : false
    } ],
    "factory" : {
      "chocolates" : [ ],
      "id" : "3",
      "name" : "The best",
      "businessHours" : "08:00 - 22:00",
      "isOpen" : true,
      "location" : {
        "longitude" : 21.3254,
        "latitude" : 25.7841234,
        "address" : {
          "street" : "Miroslava Antica 13",
          "city" : "Beocin",
          "postalCode" : "21300"
        }
      },
      "picture" : "https://w7.pngwing.com/pngs/12/661/png-transparent-danganronpa-trigger-happy-havoc-danganronpa-2-goodbye-despair-monokuma-1-t-shirt-manga-t-shirt-white-carnivoran-manga-thumbnail.png",
      "rating" : 3.1666666666666665
    },
    "id" : "S4JFKE0QF2",
    "chocolateIds" : [ "5", "5" ],
    "date" : "2024-06-30T15:15:41.9989413",
    "factoryId" : "3",
    "price" : 7.0,
    "customer" : "Milan Milanovic",
    "status" : "InProgress",
    "userId" : "5"
  },
  "S8MWQ7GZKI" : {
    "chocolates" : [ {
      "id" : "5",
      "name" : "Milka cokolada",
      "price" : 3.5,
      "type" : "Cokolada za jelo",
      "flavor" : "mlecna",
      "grams" : 300.0,
      "description" : "Najlepsa cokolada na svetu!",
      "picture" : "https://encrypted-tbn0.gstatic.com/images?q=tbn:ANd9GcRM1bjLuveRZ6g0nUu_L_XeaMdK3oiyDk_HwA&s",
      "stockQuantity" : 35,
      "isInStock" : true,
      "fabricId" : "3",
      "isDeleted" : false
    }, {
      "id" : "7",
      "name" : "daadad",
      "price" : 100.0,
      "type" : "aaaaaaaa",
      "flavor" : "aaaaaaaaa",
      "grams" : 22.0,
      "description" : "aaaaaaaa",
      "picture" : "aaaaaaaaaaaaaa",
      "stockQuantity" : 3,
      "isInStock" : true,
      "fabricId" : "3",
      "isDeleted" : false
    } ],
    "factory" : {
      "chocolates" : [ ],
      "id" : "3",
      "name" : "The best",
      "businessHours" : "08:00 - 22:00",
      "isOpen" : true,
      "location" : {
        "longitude" : 21.3254,
        "latitude" : 25.7841234,
        "address" : {
          "street" : "Miroslava Antica 13",
          "city" : "Beocin",
          "postalCode" : "21300"
        }
      },
      "picture" : "https://w7.pngwing.com/pngs/12/661/png-transparent-danganronpa-trigger-happy-havoc-danganronpa-2-goodbye-despair-monokuma-1-t-shirt-manga-t-shirt-white-carnivoran-manga-thumbnail.png",
      "rating" : 3.1666666666666665
    },
    "id" : "S8MWQ7GZKI",
    "chocolateIds" : [ "5", "5", "5", "7", "7" ],
    "date" : "2024-06-30T14:25:34.717622",
    "factoryId" : "3",
    "price" : 210.5,
    "customer" : "Milan Milanovic",
    "status" : "InProgress",
    "userId" : "5"
  },
  "F6J5BAB4VI" : {
    "chocolates" : [ ],
    "id" : "F6J5BAB4VI",
    "chocolateIds" : [ "1" ],
    "date" : "2024-07-02T02:00:01.332502000",
    "factoryId" : "2",
    "price" : 2.99,
    "customer" : "Milan Milanovic",
    "status" : "InProgress",
    "userId" : "5"
  },
  "7307S22XBT" : {
    "chocolates" : [ {
      "id" : "5",
      "name" : "Milka cokolada",
      "price" : 3.5,
      "type" : "Cokolada za jelo",
      "flavor" : "mlecna",
      "grams" : 300.0,
      "description" : "Najlepsa cokolada na svetu!",
      "picture" : "https://encrypted-tbn0.gstatic.com/images?q=tbn:ANd9GcRM1bjLuveRZ6g0nUu_L_XeaMdK3oiyDk_HwA&s",
      "stockQuantity" : 35,
      "isInStock" : true,
      "fabricId" : "3",
      "isDeleted" : false
    } ],
    "factory" : {
      "chocolates" : [ ],
      "id" : "3",
      "name" : "The best",
      "businessHours" : "08:00 - 22:00",
      "isOpen" : true,
      "location" : {
        "longitude" : 21.3254,
        "latitude" : 25.7841234,
        "address" : {
          "street" : "Miroslava Antica 13",
          "city" : "Beocin",
          "postalCode" : "21300"
        }
      },
      "picture" : "https://w7.pngwing.com/pngs/12/661/png-transparent-danganronpa-trigger-happy-havoc-danganronpa-2-goodbye-despair-monokuma-1-t-shirt-manga-t-shirt-white-carnivoran-manga-thumbnail.png",
      "rating" : 3.1666666666666665
    },
    "id" : "7307S22XBT",
    "chocolateIds" : [ "5", "5", "5" ],
    "date" : "2024-06-30T15:19:21.305251",
    "factoryId" : "3",
    "price" : 10.5,
    "customer" : "Milan Milanovic",
    "status" : "InProgress",
    "userId" : "5"
  },
  "VC73K88LU9" : {
    "chocolates" : [ {
      "id" : "5",
      "name" : "Milka cokolada",
      "price" : 3.5,
      "type" : "Cokolada za jelo",
      "flavor" : "mlecna",
      "grams" : 300.0,
      "description" : "Najlepsa cokolada na svetu!",
      "picture" : "https://encrypted-tbn0.gstatic.com/images?q=tbn:ANd9GcRM1bjLuveRZ6g0nUu_L_XeaMdK3oiyDk_HwA&s",
      "stockQuantity" : 35,
      "isInStock" : true,
      "fabricId" : "3",
      "isDeleted" : false
    }, {
      "id" : "7",
      "name" : "daadad",
      "price" : 100.0,
      "type" : "aaaaaaaa",
      "flavor" : "aaaaaaaaa",
      "grams" : 22.0,
      "description" : "aaaaaaaa",
      "picture" : "aaaaaaaaaaaaaa",
      "stockQuantity" : 3,
      "isInStock" : true,
      "fabricId" : "3",
      "isDeleted" : false
    } ],
    "factory" : {
      "chocolates" : [ ],
      "id" : "3",
      "name" : "The best",
      "businessHours" : "08:00 - 22:00",
      "isOpen" : true,
      "location" : {
        "longitude" : 21.3254,
        "latitude" : 25.7841234,
        "address" : {
          "street" : "Miroslava Antica 13",
          "city" : "Beocin",
          "postalCode" : "21300"
        }
      },
      "picture" : "https://w7.pngwing.com/pngs/12/661/png-transparent-danganronpa-trigger-happy-havoc-danganronpa-2-goodbye-despair-monokuma-1-t-shirt-manga-t-shirt-white-carnivoran-manga-thumbnail.png",
      "rating" : 3.1666666666666665
    },
    "id" : "VC73K88LU9",
    "chocolateIds" : [ "5", "5", "7" ],
    "date" : "2024-06-30T14:43:47.682621",
    "factoryId" : "3",
    "price" : 107.0,
    "customer" : "Milan Milanovic",
    "status" : "InProgress",
    "userId" : "5"
  },
  "TPLWR4SGMG" : {
    "chocolates" : [ {
      "id" : "5",
      "name" : "Milka cokolada",
      "price" : 3.5,
      "type" : "Cokolada za jelo",
      "flavor" : "mlecna",
      "grams" : 300.0,
      "description" : "Najlepsa cokolada na svetu!",
      "picture" : "https://encrypted-tbn0.gstatic.com/images?q=tbn:ANd9GcRM1bjLuveRZ6g0nUu_L_XeaMdK3oiyDk_HwA&s",
      "stockQuantity" : 35,
      "isInStock" : true,
      "fabricId" : "3",
      "isDeleted" : false
    }, {
      "id" : "7",
      "name" : "daadad",
      "price" : 100.0,
      "type" : "aaaaaaaa",
      "flavor" : "aaaaaaaaa",
      "grams" : 22.0,
      "description" : "aaaaaaaa",
      "picture" : "aaaaaaaaaaaaaa",
      "stockQuantity" : 3,
      "isInStock" : true,
      "fabricId" : "3",
      "isDeleted" : false
    } ],
    "factory" : {
      "chocolates" : [ ],
      "id" : "3",
      "name" : "The best",
      "businessHours" : "08:00 - 22:00",
      "isOpen" : true,
      "location" : {
        "longitude" : 21.3254,
        "latitude" : 25.7841234,
        "address" : {
          "street" : "Miroslava Antica 13",
          "city" : "Beocin",
          "postalCode" : "21300"
        }
      },
      "picture" : "https://w7.pngwing.com/pngs/12/661/png-transparent-danganronpa-trigger-happy-havoc-danganronpa-2-goodbye-despair-monokuma-1-t-shirt-manga-t-shirt-white-carnivoran-manga-thumbnail.png",
      "rating" : 3.1666666666666665
    },
    "id" : "TPLWR4SGMG",
    "chocolateIds" : [ "7", "5" ],
    "date" : "2024-06-30T14:54:12.9185505",
    "factoryId" : "3",
    "price" : 103.5,
    "customer" : "Milan Milanovic",
    "status" : "InProgress",
    "userId" : "5"
  },
  "25V1V6M2Q0" : {
    "chocolates" : [ {
      "id" : "5",
      "name" : "Milka cokolada",
      "price" : 3.5,
      "type" : "Cokolada za jelo",
      "flavor" : "mlecna",
      "grams" : 300.0,
      "description" : "Najlepsa cokolada na svetu!",
      "picture" : "https://encrypted-tbn0.gstatic.com/images?q=tbn:ANd9GcRM1bjLuveRZ6g0nUu_L_XeaMdK3oiyDk_HwA&s",
      "stockQuantity" : 35,
      "isInStock" : true,
      "fabricId" : "3",
      "isDeleted" : false
    } ],
    "factory" : {
      "chocolates" : [ ],
      "id" : "3",
      "name" : "The best",
      "businessHours" : "08:00 - 22:00",
      "isOpen" : true,
      "location" : {
        "longitude" : 21.3254,
        "latitude" : 25.7841234,
        "address" : {
          "street" : "Miroslava Antica 13",
          "city" : "Beocin",
          "postalCode" : "21300"
        }
      },
      "picture" : "https://w7.pngwing.com/pngs/12/661/png-transparent-danganronpa-trigger-happy-havoc-danganronpa-2-goodbye-despair-monokuma-1-t-shirt-manga-t-shirt-white-carnivoran-manga-thumbnail.png",
      "rating" : 3.1666666666666665
    },
    "id" : "25V1V6M2Q0",
    "chocolateIds" : [ "5", "5" ],
    "date" : "2024-06-30T15:19:29.132785",
    "factoryId" : "3",
    "price" : 7.0,
    "customer" : "Milan Milanovic",
    "status" : "InProgress",
    "userId" : "5"
  },
  "E1FDOL8V2O" : {
    "chocolates" : [ {
      "id" : "5",
      "name" : "Milka cokolada",
      "price" : 3.5,
      "type" : "Cokolada za jelo",
      "flavor" : "mlecna",
      "grams" : 300.0,
      "description" : "Najlepsa cokolada na svetu!",
      "picture" : "https://encrypted-tbn0.gstatic.com/images?q=tbn:ANd9GcRM1bjLuveRZ6g0nUu_L_XeaMdK3oiyDk_HwA&s",
      "stockQuantity" : 35,
      "isInStock" : true,
      "fabricId" : "3",
      "isDeleted" : false
    } ],
    "factory" : {
      "chocolates" : [ ],
      "id" : "3",
      "name" : "The best",
      "businessHours" : "08:00 - 22:00",
      "isOpen" : true,
      "location" : {
        "longitude" : 21.3254,
        "latitude" : 25.7841234,
        "address" : {
          "street" : "Miroslava Antica 13",
          "city" : "Beocin",
          "postalCode" : "21300"
        }
      },
      "picture" : "https://w7.pngwing.com/pngs/12/661/png-transparent-danganronpa-trigger-happy-havoc-danganronpa-2-goodbye-despair-monokuma-1-t-shirt-manga-t-shirt-white-carnivoran-manga-thumbnail.png",
      "rating" : 3.1666666666666665
    },
    "id" : "E1FDOL8V2O",
    "chocolateIds" : [ "5", "5" ],
    "date" : "2024-06-30T15:04:06.9238907",
    "factoryId" : "3",
    "price" : 7.0,
    "customer" : "Milan Milanovic",
    "status" : "InProgress",
    "userId" : "5"
  },
  "8T50OKHWZN" : {
    "chocolates" : [ {
      "id" : "3",
      "name" : "Milicina Cokolada",
      "price" : 21.25,
      "type" : "cokolada za kuvanje",
      "flavor" : "gorka",
      "grams" : 200.0,
      "description" : "prelepa cokolada",
      "picture" : "21a",
      "stockQuantity" : 0,
      "isInStock" : false,
      "fabricId" : "4",
      "isDeleted" : false
    } ],
    "factory" : {
      "chocolates" : [ ],
      "id" : "4",
      "name" : "Milka",
      "businessHours" : "09:00 - 20:00",
      "isOpen" : false,
      "location" : {
        "longitude" : 74.1234512,
        "latitude" : 54.7841234,
        "address" : {
          "street" : "Bulevar Oslobodjenja 12",
          "city" : "Novi Sad",
          "postalCode" : "21000"
        }
      },
      "picture" : "https://w7.pngwing.com/pngs/12/661/png-transparent-danganronpa-trigger-happy-havoc-danganronpa-2-goodbye-despair-monokuma-1-t-shirt-manga-t-shirt-white-carnivoran-manga-thumbnail.png",
      "rating" : 2.2
    },
    "id" : "8T50OKHWZN",
    "chocolateIds" : [ "3", "3" ],
    "date" : "2024-07-02T01:13:01.91645300",
    "factoryId" : "4",
    "price" : 42.5,
    "customer" : "nikola lakic",
    "status" : "Accepted",
    "userId" : "3"
  },
  "S6POO7VOYF" : {
    "chocolates" : [ {
      "id" : "5",
      "name" : "Milka cokolada",
      "price" : 3.5,
      "type" : "Cokolada za jelo",
      "flavor" : "mlecna",
      "grams" : 300.0,
      "description" : "Najlepsa cokolada na svetu!",
      "picture" : "https://encrypted-tbn0.gstatic.com/images?q=tbn:ANd9GcRM1bjLuveRZ6g0nUu_L_XeaMdK3oiyDk_HwA&s",
      "stockQuantity" : 35,
      "isInStock" : true,
      "fabricId" : "3",
      "isDeleted" : false
    } ],
    "factory" : {
      "chocolates" : [ ],
      "id" : "3",
      "name" : "The best",
      "businessHours" : "08:00 - 22:00",
      "isOpen" : true,
      "location" : {
        "longitude" : 21.3254,
        "latitude" : 25.7841234,
        "address" : {
          "street" : "Miroslava Antica 13",
          "city" : "Beocin",
          "postalCode" : "21300"
        }
      },
      "picture" : "https://w7.pngwing.com/pngs/12/661/png-transparent-danganronpa-trigger-happy-havoc-danganronpa-2-goodbye-despair-monokuma-1-t-shirt-manga-t-shirt-white-carnivoran-manga-thumbnail.png",
      "rating" : 3.1666666666666665
    },
    "id" : "S6POO7VOYF",
    "chocolateIds" : [ "5", "5" ],
    "date" : "2024-06-30T15:08:48.6758252",
    "factoryId" : "3",
    "price" : 7.0,
    "customer" : "Milan Milanovic",
    "status" : "InProgress",
    "userId" : "5"
  },
  "0LL31VL0EI" : {
    "chocolates" : [ {
      "id" : "5",
      "name" : "Milka cokolada",
      "price" : 3.5,
      "type" : "Cokolada za jelo",
      "flavor" : "mlecna",
      "grams" : 300.0,
      "description" : "Najlepsa cokolada na svetu!",
      "picture" : "https://encrypted-tbn0.gstatic.com/images?q=tbn:ANd9GcRM1bjLuveRZ6g0nUu_L_XeaMdK3oiyDk_HwA&s",
      "stockQuantity" : 35,
      "isInStock" : true,
      "fabricId" : "3",
      "isDeleted" : false
    }, {
      "id" : "7",
      "name" : "daadad",
      "price" : 100.0,
      "type" : "aaaaaaaa",
      "flavor" : "aaaaaaaaa",
      "grams" : 22.0,
      "description" : "aaaaaaaa",
      "picture" : "aaaaaaaaaaaaaa",
      "stockQuantity" : 3,
      "isInStock" : true,
      "fabricId" : "3",
      "isDeleted" : false
    } ],
    "factory" : {
      "chocolates" : [ ],
      "id" : "3",
      "name" : "The best",
      "businessHours" : "08:00 - 22:00",
      "isOpen" : true,
      "location" : {
        "longitude" : 21.3254,
        "latitude" : 25.7841234,
        "address" : {
          "street" : "Miroslava Antica 13",
          "city" : "Beocin",
          "postalCode" : "21300"
        }
      },
      "picture" : "https://w7.pngwing.com/pngs/12/661/png-transparent-danganronpa-trigger-happy-havoc-danganronpa-2-goodbye-despair-monokuma-1-t-shirt-manga-t-shirt-white-carnivoran-manga-thumbnail.png",
      "rating" : 3.1666666666666665
    },
    "id" : "0LL31VL0EI",
    "chocolateIds" : [ "5", "5", "5", "7" ],
    "date" : "2024-06-30T14:50:27.3190649",
    "factoryId" : "3",
    "price" : 110.5,
    "customer" : "Milan Milanovic",
    "status" : "Cancelled",
    "userId" : "5"
  },
  "WOII8S99FJ" : {
    "chocolates" : [ {
      "id" : "5",
      "name" : "Milka cokolada",
      "price" : 3.5,
      "type" : "Cokolada za jelo",
      "flavor" : "mlecna",
      "grams" : 300.0,
      "description" : "Najlepsa cokolada na svetu!",
      "picture" : "https://encrypted-tbn0.gstatic.com/images?q=tbn:ANd9GcRM1bjLuveRZ6g0nUu_L_XeaMdK3oiyDk_HwA&s",
      "stockQuantity" : 35,
      "isInStock" : true,
      "fabricId" : "3",
      "isDeleted" : false
    } ],
    "factory" : {
      "chocolates" : [ ],
      "id" : "3",
      "name" : "The best",
      "businessHours" : "08:00 - 22:00",
      "isOpen" : true,
      "location" : {
        "longitude" : 21.3254,
        "latitude" : 25.7841234,
        "address" : {
          "street" : "Miroslava Antica 13",
          "city" : "Beocin",
          "postalCode" : "21300"
        }
      },
      "picture" : "https://w7.pngwing.com/pngs/12/661/png-transparent-danganronpa-trigger-happy-havoc-danganronpa-2-goodbye-despair-monokuma-1-t-shirt-manga-t-shirt-white-carnivoran-manga-thumbnail.png",
      "rating" : 3.1666666666666665
    },
    "id" : "WOII8S99FJ",
    "chocolateIds" : [ "5", "5" ],
    "date" : "2024-06-30T16:15:27.878856",
    "factoryId" : "3",
    "price" : 6.65,
    "customer" : "Milan Milanovic",
    "status" : "Declined",
    "userId" : "5"
  },
  "FZO4NXR1Q6" : {
    "chocolates" : [ {
      "id" : "5",
      "name" : "Milka cokolada",
      "price" : 3.5,
      "type" : "Cokolada za jelo",
      "flavor" : "mlecna",
      "grams" : 300.0,
      "description" : "Najlepsa cokolada na svetu!",
      "picture" : "https://encrypted-tbn0.gstatic.com/images?q=tbn:ANd9GcRM1bjLuveRZ6g0nUu_L_XeaMdK3oiyDk_HwA&s",
      "stockQuantity" : 35,
      "isInStock" : true,
      "fabricId" : "3",
      "isDeleted" : false
    } ],
    "factory" : {
      "chocolates" : [ ],
      "id" : "3",
      "name" : "The best",
      "businessHours" : "08:00 - 22:00",
      "isOpen" : true,
      "location" : {
        "longitude" : 21.3254,
        "latitude" : 25.7841234,
        "address" : {
          "street" : "Miroslava Antica 13",
          "city" : "Beocin",
          "postalCode" : "21300"
        }
      },
      "picture" : "https://w7.pngwing.com/pngs/12/661/png-transparent-danganronpa-trigger-happy-havoc-danganronpa-2-goodbye-despair-monokuma-1-t-shirt-manga-t-shirt-white-carnivoran-manga-thumbnail.png",
      "rating" : 3.1666666666666665
    },
    "id" : "FZO4NXR1Q6",
    "chocolateIds" : [ "5", "5" ],
    "date" : "2024-07-01T02:56:07.620737700",
    "factoryId" : "3",
    "price" : 7.0,
    "customer" : "Milan Milanovic",
    "status" : "InProgress",
    "userId" : "5"
  },
  "6U2DHBLJRP" : {
    "chocolates" : [ {
      "id" : "7",
      "name" : "daadad",
      "price" : 100.0,
      "type" : "aaaaaaaa",
      "flavor" : "aaaaaaaaa",
      "grams" : 22.0,
      "description" : "aaaaaaaa",
      "picture" : "aaaaaaaaaaaaaa",
      "stockQuantity" : 3,
      "isInStock" : true,
      "fabricId" : "3",
      "isDeleted" : false
    } ],
    "factory" : {
      "chocolates" : [ ],
      "id" : "3",
      "name" : "The best",
      "businessHours" : "08:00 - 22:00",
      "isOpen" : true,
      "location" : {
        "longitude" : 21.3254,
        "latitude" : 25.7841234,
        "address" : {
          "street" : "Miroslava Antica 13",
          "city" : "Beocin",
          "postalCode" : "21300"
        }
      },
      "picture" : "https://w7.pngwing.com/pngs/12/661/png-transparent-danganronpa-trigger-happy-havoc-danganronpa-2-goodbye-despair-monokuma-1-t-shirt-manga-t-shirt-white-carnivoran-manga-thumbnail.png",
      "rating" : 3.1666666666666665
    },
    "id" : "6U2DHBLJRP",
    "chocolateIds" : [ "7", "7" ],
    "date" : "2024-06-30T14:27:38.2382131",
    "factoryId" : "3",
    "price" : 200.0,
    "customer" : "Milan Milanovic",
    "status" : "Accepted",
    "userId" : "5"
  }
}